{
  "document_metadata": {
    "page_number": "5",
    "document_number": "616",
    "date": "02/24/22",
    "document_type": "court document",
    "has_handwriting": false,
    "has_stamps": false
  },
  "full_text": "Case 1:20-cr-00330-PAE Document 616 Filed 02/24/22 Page 5 of 32\n\nConstitutional Provisions\n\nU.S. Const. amends. V .............................................................................. 1, 6, 23\nU.S. Const. amends. VI ............................................................................ 1, 6, 23\n\nv\n\nDOJ-OGR-00009195",
  "text_blocks": [
    {
      "type": "printed",
      "content": "Case 1:20-cr-00330-PAE Document 616 Filed 02/24/22 Page 5 of 32",
      "position": "header"
    },
    {
      "type": "printed",
      "content": "Constitutional Provisions",
      "position": "top"
    },
    {
      "type": "printed",
      "content": "U.S. Const. amends. V .............................................................................. 1, 6, 23\nU.S. Const. amends. VI ............................................................................ 1, 6, 23",
      "position": "middle"
    },
    {
      "type": "printed",
      "content": "v",
      "position": "bottom"
    },
    {
      "type": "printed",
      "content": "DOJ-OGR-00009195",
      "position": "footer"
    }
  ],
  "entities": {
    "people": [],
    "organizations": [
      "U.S."
    ],
    "locations": [],
    "dates": [
      "02/24/22"
    ],
    "reference_numbers": [
      "1:20-cr-00330-PAE",
      "616",
      "DOJ-OGR-00009195"
    ]
  },
  "additional_notes": "The document appears to be a court filing with references to the U.S. Constitution. The quality is clear, and there are no visible redactions or damage."
}