{
  "document_metadata": {
    "page_number": "1",
    "document_number": "675-1",
    "date": "06/25/22",
    "document_type": "Declaration",
    "has_handwriting": false,
    "has_stamps": false
  },
  "full_text": "Case 1:20-cr-00330-PAE Document 675-1 Filed 06/25/22 Page 1 of 2\n\nUNITED STATES DISTRICT COURT\nSOUTHERN DISTRICT OF NEW YORK\n\nUNITED STATES OF AMERICA,\n\n-v-\n\nGHISLAINE MAXWELL,\n\nDefendant.\n\nCase No. 20-CR-330 (AJN)\n\nDECLARATION OF ROBERT Y. LEWIS\n\nRobert Y. Lewis declares under penalty of perjury as follows:\n\n1. I represent Sarah Ransome and Elizabeth Stein, two victims of the sex trafficking conspiracy of Jeffrey Epstein, Ghislaine Maxwell and others.\n\n2. I make this declaration in support of their motion to speak at the upcoming sentencing of Ghislaine Maxwell who was convicted of five sex trafficking criminal counts - Nos. 1 and 3-6 of the government's Second Superseding indictment.\n\n3. On May 9, 2022, I emailed Dawn Donino at the probation office of the Southern District of New York to inquire to whom and when to submit Victim Impact Statements for Ms. Ransome and Ms. Stein.\n\n4. On May 9, 2022, Ms. Donino emailed back to say that I should communicate with Probation Officer Ashley Geiser.\n\n5. On May 10, 2022, Ms. Geiser emailed me saying that she was completing the presentence investigation for Ms. Maxwell and directed that I submit any Victim Impact Statement to her by June 3 for inclusion in the Presentence Report.\n\n6. On May 31, 2022, I emailed the Victim Impact Statement of Sarah Ransome to Ms. Geiser.\n\nDOJ-OGR-00010713",
  "text_blocks": [
    {
      "type": "printed",
      "content": "Case 1:20-cr-00330-PAE Document 675-1 Filed 06/25/22 Page 1 of 2",
      "position": "header"
    },
    {
      "type": "printed",
      "content": "UNITED STATES DISTRICT COURT SOUTHERN DISTRICT OF NEW YORK",
      "position": "header"
    },
    {
      "type": "printed",
      "content": "UNITED STATES OF AMERICA, -v- GHISLAINE MAXWELL, Defendant. Case No. 20-CR-330 (AJN)",
      "position": "middle"
    },
    {
      "type": "printed",
      "content": "DECLARATION OF ROBERT Y. LEWIS Robert Y. Lewis declares under penalty of perjury as follows:",
      "position": "middle"
    },
    {
      "type": "printed",
      "content": "1. I represent Sarah Ransome and Elizabeth Stein, two victims of the sex trafficking conspiracy of Jeffrey Epstein, Ghislaine Maxwell and others. 2. I make this declaration in support of their motion to speak at the upcoming sentencing of Ghislaine Maxwell who was convicted of five sex trafficking criminal counts - Nos. 1 and 3-6 of the government's Second Superseding indictment. 3. On May 9, 2022, I emailed Dawn Donino at the probation office of the Southern District of New York to inquire to whom and when to submit Victim Impact Statements for Ms. Ransome and Ms. Stein. 4. On May 9, 2022, Ms. Donino emailed back to say that I should communicate with Probation Officer Ashley Geiser. 5. On May 10, 2022, Ms. Geiser emailed me saying that she was completing the presentence investigation for Ms. Maxwell and directed that I submit any Victim Impact Statement to her by June 3 for inclusion in the Presentence Report. 6. On May 31, 2022, I emailed the Victim Impact Statement of Sarah Ransome to Ms. Geiser.",
      "position": "middle"
    },
    {
      "type": "printed",
      "content": "DOJ-OGR-00010713",
      "position": "footer"
    }
  ],
  "entities": {
    "people": [
      "Robert Y. Lewis",
      "Sarah Ransome",
      "Elizabeth Stein",
      "Jeffrey Epstein",
      "Ghislaine Maxwell",
      "Dawn Donino",
      "Ashley Geiser"
    ],
    "organizations": [
      "UNITED STATES DISTRICT COURT",
      "SOUTHERN DISTRICT OF NEW YORK",
      "Probation Office"
    ],
    "locations": [
      "New York"
    ],
    "dates": [
      "May 9, 2022",
      "May 10, 2022",
      "May 31, 2022",
      "June 3",
      "06/25/22"
    ],
    "reference_numbers": [
      "20-CR-330 (AJN)",
      "675-1",
      "DOJ-OGR-00010713"
    ]
  },
  "additional_notes": "The document appears to be a formal declaration in a court case, with no visible redactions or damage."
}