{
  "document_metadata": {
    "page_number": "5",
    "document_number": null,
    "date": null,
    "document_type": "List of Trilateral Commission Members",
    "has_handwriting": false,
    "has_stamps": false
  },
  "full_text": "Trilateral Commission Members Page 5 of 9 Count Marice Lippens, Chairman, Fortis, Brussels Winston Lord, Former U.S. Assistant Secretary of State for East Asian and Pacific Affairs; former U.S. Ambassador to China E. Peter Lougheed, former premier of Alberta Cees Maas, former Treasurer of the Dutch Government Ahmad Syafill Maarif, Chairman, Muhammadiyah Movement, Indonesia H. Harrison McCain, Chairman of the Board, McCain Foods Limited, Toronto Hugh L. McColl, Jr., Chairman, President and Chief Executive Officer, NationsBank Corporation William J. McDonough, President, Federal Reserve Bank of New York Roy MacLaren, former Candian high commissioner to the U.K. Whitney MacMillan, Former Chairman of the Board and Chief Executive Officer, Cargill, Inc. Robert S. McNamara, Lifetime Trustee, former Secretary of Defense, former President, World Bank Antonio Mader, President, San Luis Corporacion, S.A. de C.V., Mexico City Jessica T. Mathews, President, Carnegie Endowment for International Peace Abel Matutes, Chairman, Empresas Matutes Francis Maud, Member of the British Parliament Sir Deryck C. Maughan, vice Chairman, Citigroup, New York Jay Mazur, President Emeritus, Union of Neeletrades, Industrial and Textile Employees, AFL-CIO Peter Mitterbauer, President, the Federation of Austrian Industry, Vienna Kiichi Miyazawa, former prime Minister of Japan Thierry de Montbrial, Director, French Institute for International Relations Sir Mark Moody-Stuart, former Chairman, Royal Dutch/Shell Group Jiro Murase, Managing partner, Bingham Dana Murase Salomom Smith Barney Holdings Inc. Jay Mazur, President, Union of Needletrades, Industrial and Textile Employees (UNITE), AFL-CIO, CLC Yuang Ming, Director, Institute of international relations, Peking University Mario Monti, Director-General, World Trade Organization Yoshiji Nogami, Former Vice Minister for Foreign Affairs, Japan Lucio A. Noto, Chairman and Chief Executive Officer Mobil Corporation Joseph S. Nye, Jr., Dean, John F Kennedy School of Government, Harvard University; former U.S. Assistant Secretary of Defense for International Security Affairs Shijuro Ogata, former Deputy Governor, Japan Development Bank Michel Oksenberg, Senior Fellow, Asia Pacific Research Center Stanford University; former Staff Member (China), U.S. National Security Council Andrzej Olechowski, Chairman, Civic Platform, Warsaw Michael O'Neil, North American Director, the Trilateral Commission Lucas Papademos, Governor of the Bank of Greece, Athens Schelto Patijn, former mayor of Amsterdam, The Netherlands James A. Pattison, Chairman, President and Chief Executive Officer Jim Pattison Group Inc., Vancouver William Perry, Michael and Barbara Berberian Professor Stanford University; former U.S. Secretary of Defense Michael E. J. Phelps, Chairman and Chief Executive Officer Westcoast Energy Inc., Vancouver Colin L. Powell, U.S. Secretary of State Alessandro Profumo, Managing Director, Unicredito Italiano, Milan http://www.biblebelievers.org.au/weektc.htm Page 58 of 151 Public Records Request No.: 171295/2005 DOJ-OGR-00032097",
  "text_blocks": [
    {
      "type": "printed",
      "content": "Trilateral Commission Members",
      "position": "header"
    },
    {
      "type": "printed",
      "content": "Page 5 of 9",
      "position": "header"
    },
    {
      "type": "printed",
      "content": "Count Marice Lippens, Chairman, Fortis, Brussels\nWinston Lord, Former U.S. Assistant Secretary of State for East Asian and Pacific Affairs; former U.S. Ambassador to China\nE. Peter Lougheed, former premier of Alberta\nCees Maas, former Treasurer of the Dutch Government\nAhmad Syafill Maarif, Chairman, Muhammadiyah Movement, Indonesia\nH. Harrison McCain, Chairman of the Board, McCain Foods Limited, Toronto\nHugh L. McColl, Jr., Chairman, President and Chief Executive Officer, NationsBank Corporation\nWilliam J. McDonough, President, Federal Reserve Bank of New York\nRoy MacLaren, former Candian high commissioner to the U.K.\nWhitney MacMillan, Former Chairman of the Board and Chief Executive Officer, Cargill, Inc.\nRobert S. McNamara, Lifetime Trustee, former Secretary of Defense, former President, World Bank\nAntonio Mader, President, San Luis Corporacion, S.A. de C.V., Mexico City\nJessica T. Mathews, President, Carnegie Endowment for International Peace\nAbel Matutes, Chairman, Empresas Matutes\nFrancis Maud, Member of the British Parliament\nSir Deryck C. Maughan, vice Chairman, Citigroup, New York\nJay Mazur, President Emeritus, Union of Neeletrades, Industrial and Textile Employees, AFL-CIO\nPeter Mitterbauer, President, the Federation of Austrian Industry, Vienna\nKiichi Miyazawa, former prime Minister of Japan\nThierry de Montbrial, Director, French Institute for International Relations\nSir Mark Moody-Stuart, former Chairman, Royal Dutch/Shell Group\nJiro Murase, Managing partner, Bingham Dana Murase Salomom Smith Barney Holdings Inc.\nJay Mazur, President, Union of Needletrades, Industrial and Textile Employees (UNITE), AFL-CIO, CLC\nYuang Ming, Director, Institute of international relations, Peking University\nMario Monti, Director-General, World Trade Organization\nYoshiji Nogami, Former Vice Minister for Foreign Affairs, Japan\nLucio A. Noto, Chairman and Chief Executive Officer Mobil Corporation\nJoseph S. Nye, Jr., Dean, John F Kennedy School of Government, Harvard University; former U.S. Assistant Secretary of Defense for International Security Affairs\nShijuro Ogata, former Deputy Governor, Japan Development Bank\nMichel Oksenberg, Senior Fellow, Asia Pacific Research Center Stanford University; former Staff Member (China), U.S. National Security Council\nAndrzej Olechowski, Chairman, Civic Platform, Warsaw\nMichael O'Neil, North American Director, the Trilateral Commission Lucas Papademos, Governor of the Bank of Greece, Athens\nSchelto Patijn, former mayor of Amsterdam, The Netherlands\nJames A. Pattison, Chairman, President and Chief Executive Officer Jim Pattison Group Inc., Vancouver\nWilliam Perry, Michael and Barbara Berberian Professor Stanford University; former U.S. Secretary of Defense\nMichael E. J. Phelps, Chairman and Chief Executive Officer Westcoast Energy Inc., Vancouver\nColin L. Powell, U.S. Secretary of State\nAlessandro Profumo, Managing Director, Unicredito Italiano, Milan",
      "position": "main content"
    },
    {
      "type": "printed",
      "content": "http://www.biblebelievers.org.au/weektc.htm Page 58 of 151",
      "position": "footer"
    },
    {
      "type": "printed",
      "content": "Public Records Request No.: 171295/2005",
      "position": "footer"
    },
    {
      "type": "printed",
      "content": "DOJ-OGR-00032097",
      "position": "footer"
    }
  ],
  "entities": {
    "people": [
      "Count Marice Lippens",
      "Winston Lord",
      "E. Peter Lougheed",
      "Cees Maas",
      "Ahmad Syafill Maarif",
      "H. Harrison McCain",
      "Hugh L. McColl, Jr.",
      "William J. McDonough",
      "Roy MacLaren",
      "Whitney MacMillan",
      "Robert S. McNamara",
      "Antonio Mader",
      "Jessica T. Mathews",
      "Abel Matutes",
      "Francis Maud",
      "Sir Deryck C. Maughan",
      "Jay Mazur",
      "Peter Mitterbauer",
      "Kiichi Miyazawa",
      "Thierry de Montbrial",
      "Sir Mark Moody-Stuart",
      "Jiro Murase",
      "Jay Mazur",
      "Yuang Ming",
      "Mario Monti",
      "Yoshiji Nogami",
      "Lucio A. Noto",
      "Joseph S. Nye, Jr.",
      "Shijuro Ogata",
      "Michel Oksenberg",
      "Andrzej Olechowski",
      "Michael O'Neil",
      "Lucas Papademos",
      "Schelto Patijn",
      "James A. Pattison",
      "William Perry",
      "Michael E. J. Phelps",
      "Colin L. Powell",
      "Alessandro Profumo"
    ],
    "organizations": [
      "Fortis",
      "U.S. State Department",
      "Muhammadiyah Movement",
      "McCain Foods Limited",
      "NationsBank Corporation",
      "Federal Reserve Bank of New York",
      "Cargill, Inc.",
      "World Bank",
      "San Luis Corporacion, S.A. de C.V.",
      "Carnegie Endowment for International Peace",
      "Empresas Matutes",
      "British Parliament",
      "Citigroup",
      "Union of Neelletrades, Industrial and Textile Employees",
      "AFL-CIO",
      "Federation of Austrian Industry",
      "French Institute for International Relations",
      "Royal Dutch/Shell Group",
      "Bingham Dana Murase Salomom Smith Barney Holdings Inc.",
      "Union of Needletrades, Industrial and Textile Employees (UNITE)",
      "CLC",
      "Peking University",
      "World Trade Organization",
      "Mobil Corporation",
      "John F Kennedy School of Government",
      "Harvard University",
      "Japan Development Bank",
      "Asia Pacific Research Center",
      "Stanford University",
      "U.S. National Security Council",
      "Civic Platform",
      "Bank of Greece",
      "Jim Pattison Group Inc.",
      "Westcoast Energy Inc.",
      "Unicredito Italiano"
    ],
    "locations": [
      "Brussels",
      "China",
      "Alberta",
      "Indonesia",
      "Toronto",
      "New York",
      "U.K.",
      "Mexico City",
      "Vienna",
      "Japan",
      "Peking",
      "Athens",
      "Amsterdam",
      "Vancouver",
      "Warsaw"
    ],
    "dates": [],
    "reference_numbers": [
      "171295/2005",
      "DOJ-OGR-00032097"
    ]
  },
  "additional_notes": "The document appears to be a list of Trilateral Commission members, likely from a public records request. The text is printed and there are no handwritten notes or stamps visible. The document is page 5 of 9."
}