{
  "document_metadata": {
    "page_number": "5",
    "document_number": "DOJ-OGR-00031016",
    "date": "4/4/2006",
    "document_type": "Myspace profile and comments",
    "has_handwriting": false,
    "has_stamps": false
  },
  "full_text": "www.myspace.com/iloveanirishboi Page 5 of 10 Hate anyone: i dislike a few Take This Survey CREATE YOUR OWN! - or - GET PAID TO TAKE SURVEYS! Details Status: Orientation: Hometown: Religion: Zodiac Sign: Smoke / Drink Children: Income: you stayin .. for a long time .. lol .. he said \"thats fine with me\" lol .. but yea i hope to see you soon and dont forget to call when you get to atlanta .. lol .. love ya alot!! Daddy's LiL' Girl 3/27/2006 6:08 PM Hey ! Guess what me and jonathan went to the movies and had the best time and omg i love him 4e and then after that he came over for a little while and hung out and TOM is ONE MONTH! im EXSTATIC .. lol Well CONgRadS on Tom .. Let me be the first to say : \"WELCOME BACK\" Oh yeah and how about you come to Wellington .. and I BET I WILL GET U BACK INTO DANCING?!! xOxO.. i was so excited to keep it in so i told you about our night .. bye !!! shake your ziggy zong [&\\u2665;] 3/27/2006 12:39 PM we are taking pictures tonight =] yay.. don't forget black or blue.. cant wait to see you again!!! \\u2665 i love you poo nikxx MeG-a-LyNn 3/27/2006 12:07 PM kkkk.. lol... megan Daddy's LiL' Girl 3/27/2006 10:05 AM Hey It's been awesome talking 2 you i cant wait to meet you in person lol .. And were going to be beach buddies lol .. and mark my words im going to make http://profile.myspace.com/index.cfm?fuseaction=user.viewprofile&friendID=6573975 07/26/17 Page 10 of 95 4/4/2006 Public Records Request No.: 17-295 DOJ-OGR-00031016",
  "text_blocks": [
    {
      "type": "printed",
      "content": "www.myspace.com/iloveanirishboi",
      "position": "header"
    },
    {
      "type": "printed",
      "content": "Page 5 of 10",
      "position": "header"
    },
    {
      "type": "printed",
      "content": "Hate anyone: i dislike a few Take This Survey CREATE YOUR OWN! - or - GET PAID TO TAKE SURVEYS!",
      "position": "top"
    },
    {
      "type": "printed",
      "content": "Details Status: Orientation: Hometown: Religion: Zodiac Sign: Smoke / Drink Children: Income:",
      "position": "left"
    },
    {
      "type": "handwritten",
      "content": "you stayin .. for a long time .. lol .. he said \"thats fine with me\" lol .. but yea i hope to see you soon and dont forget to call when you get to atlanta .. lol .. love ya alot!!",
      "position": "right"
    },
    {
      "type": "printed",
      "content": "Daddy's LiL' Girl 3/27/2006 6:08 PM",
      "position": "right"
    },
    {
      "type": "handwritten",
      "content": "Hey ! Guess what me and jonathan went to the movies and had the best time and omg i love him 4e and then after that he came over for a little while and hung out and TOM is ONE MONTH! im EXSTATIC .. lol Well CONgRadS on Tom .. Let me be the first to say : \"WELCOME BACK\" Oh yeah and how about you come to Wellington .. and I BET I WILL GET U BACK INTO DANCING?!! xOxO.. i was so excited to keep it in so i told you about our night .. bye !!! shake your ziggy zong [&\\u2665;]",
      "position": "right"
    },
    {
      "type": "printed",
      "content": "3/27/2006 12:39 PM",
      "position": "right"
    },
    {
      "type": "handwritten",
      "content": "we are taking pictures tonight =] yay.. don't forget black or blue.. cant wait to see you again!!! \\u2665 i love you poo nikxx",
      "position": "right"
    },
    {
      "type": "printed",
      "content": "MeG-a-LyNn 3/27/2006 12:07 PM",
      "position": "right"
    },
    {
      "type": "handwritten",
      "content": "kkkk.. lol... megan",
      "position": "right"
    },
    {
      "type": "printed",
      "content": "Daddy's LiL' Girl 3/27/2006 10:05 AM",
      "position": "right"
    },
    {
      "type": "handwritten",
      "content": "Hey It's been awesome talking 2 you i cant wait to meet you in person lol .. And were going to be beach buddies lol .. and mark my words im going to make",
      "position": "right"
    },
    {
      "type": "printed",
      "content": "http://profile.myspace.com/index.cfm?fuseaction=user.viewprofile&friendID=6573975 07/26/17 Page 10 of 95 4/4/2006 Public Records Request No.: 17-295 DOJ-OGR-00031016",
      "position": "footer"
    }
  ],
  "entities": {
    "people": [
      "jonathan",
      "TOM",
      "nik",
      "megan"
    ],
    "organizations": [],
    "locations": [
      "Wellington",
      "atlanta"
    ],
    "dates": [
      "3/27/2006",
      "4/4/2006",
      "07/26/17"
    ],
    "reference_numbers": [
      "17-295",
      "DOJ-OGR-00031016",
      "6573975"
    ]
  },
  "additional_notes": "The document appears to be a printout of a Myspace profile and comments. Some text is redacted with black boxes. The document is likely a public records request response."
}