{
  "document_metadata": {
    "page_number": "16",
    "document_number": "153497",
    "date": "12/14/2005",
    "document_type": "Billed Usage",
    "has_handwriting": false,
    "has_stamps": false
  },
  "full_text": "153497\n12/14/2005\nBILLED USAGE 3G\nCingular\nRun Date: 12/19/05\nRun Time: 11:43:35\nATLYS Voice Usage For (917)855-3363\nAccount Number 0043811863 Bill Cycle: 2\nItem Date Time Number Called Calls To Mins Used Rate Charge Description Charge\n09/14/05 03:39P (917)855-3363 2 0.00 UNLIM MOBL TO MOBL\n194 09/14/05 03:43P 447785770009 mobile UK 1 0.00 400 ADD'L ANY TIME MIN\n195 09/14/05 04:04P (212)750-1178 INCOMING 1 0.28 ENH DISC INT DL $0.28\n196 09/14/05 04:05P (212)750-9791 INCOMING 1 0.00 CALL WAITING\n197 09/14/05 04:08P (212)750-9895 NEW YORK NY 1 0.00 400 ADD'L ANY TIME MIN\n198 09/14/05 04:18P (212)838-9514 INCOMING 4 0.00 400 ADD'L ANY TIME MIN\n199 09/14/05 05:02P (617)495-1953 INCOMING 2 0.00 400 ADD'L ANY TIME MIN\n200 09/14/05 05:05P (212)750-1176 INCOMING 1 0.00 400 ADD'L ANY TIME MIN\n201 09/14/05 05:08P (561)317-5844 WPALMBEACH FL 1 0.00 400 ADD'L ANY TIME MIN\n202 09/14/05 05:12P (212)750-9895 NEW YORK NY 2 0.00 400 ADD'L ANY TIME MIN\n203 09/14/05 05:13P (917)520-3106 NEW YORK NY 1 0.00 UNLIM MOBL TO MOBL\n204 09/14/05 05:35P (212)750-9894 INCOMING 1 0.00 400 ADD'L ANY TIME MIN\n205 09/14/05 05:39P (212)744-1600 INCOMING 1 0.00 400 ADD'L ANY TIME MIN\n206 09/14/05 05:42P (917)204-9696 NEW YORK NY 1 0.00 400 ADD'L ANY TIME MIN\n207 09/14/05 05:54P (917)204-9696 INCOMING 1 0.00 400 ADD'L ANY TIME MIN\n208 09/14/05 06:17P (310)- INCOMING 3 0.00 400 ADD'L ANY TIME MIN\n209 09/14/05 06:24P (617)491-4204 CAMBRIDGE MA 2 0.00 400 ADD'L ANY TIME MIN\n210 09/14/05 06:32P (917)855-3363 NEW YORK NY 2 0.00 UNLIM MOBL TO MOBL\n211 09/14/05 07:07P (917)855-3363 NEW YORK NY 2 0.00 MESSAGE RETRIEVAL\nMAT PROPRIETARY AND CONFIDENTIAL Page 11\nNot for use or disclosure outside Cingular Wireless and its Affiliates except under written agreement.\n07/26/17 Page 16 of 82 Public Records Request No.: 17-295 DOJ-OGR-00030734",
  "text_blocks": [
    {
      "type": "printed",
      "content": "153497\n12/14/2005\nBILLED USAGE 3G\nCingular",
      "position": "header"
    },
    {
      "type": "printed",
      "content": "Run Date: 12/19/05\nRun Time: 11:43:35\nATLYS Voice Usage For (917)855-3363\nAccount Number 0043811863 Bill Cycle: 2",
      "position": "top"
    },
    {
      "type": "printed",
      "content": "Item Date Time Number Called Calls To Mins Used Rate Charge Description Charge",
      "position": "top"
    },
    {
      "type": "printed",
      "content": "09/14/05 03:39P (917)855-3363 2 0.00 UNLIM MOBL TO MOBL\n194 09/14/05 03:43P 447785770009 mobile UK 1 0.00 400 ADD'L ANY TIME MIN\n195 09/14/05 04:04P (212)750-1178 INCOMING 1 0.28 ENH DISC INT DL $0.28\n196 09/14/05 04:05P (212)750-9791 INCOMING 1 0.00 CALL WAITING\n197 09/14/05 04:08P (212)750-9895 NEW YORK NY 1 0.00 400 ADD'L ANY TIME MIN\n198 09/14/05 04:18P (212)838-9514 INCOMING 4 0.00 400 ADD'L ANY TIME MIN\n199 09/14/05 05:02P (617)495-1953 INCOMING 2 0.00 400 ADD'L ANY TIME MIN\n200 09/14/05 05:05P (212)750-1176 INCOMING 1 0.00 400 ADD'L ANY TIME MIN\n201 09/14/05 05:08P (561)317-5844 WPALMBEACH FL 1 0.00 400 ADD'L ANY TIME MIN\n202 09/14/05 05:12P (212)750-9895 NEW YORK NY 2 0.00 400 ADD'L ANY TIME MIN\n203 09/14/05 05:13P (917)520-3106 NEW YORK NY 1 0.00 UNLIM MOBL TO MOBL\n204 09/14/05 05:35P (212)750-9894 INCOMING 1 0.00 400 ADD'L ANY TIME MIN\n205 09/14/05 05:39P (212)744-1600 INCOMING 1 0.00 400 ADD'L ANY TIME MIN\n206 09/14/05 05:42P (917)204-9696 NEW YORK NY 1 0.00 400 ADD'L ANY TIME MIN\n207 09/14/05 05:54P (917)204-9696 INCOMING 1 0.00 400 ADD'L ANY TIME MIN\n208 09/14/05 06:17P (310)- INCOMING 3 0.00 400 ADD'L ANY TIME MIN\n209 09/14/05 06:24P (617)491-4204 CAMBRIDGE MA 2 0.00 400 ADD'L ANY TIME MIN\n210 09/14/05 06:32P (917)855-3363 NEW YORK NY 2 0.00 UNLIM MOBL TO MOBL\n211 09/14/05 07:07P (917)855-3363 NEW YORK NY 2 0.00 MESSAGE RETRIEVAL",
      "position": "middle"
    },
    {
      "type": "printed",
      "content": "MAT PROPRIETARY AND CONFIDENTIAL Page 11\nNot for use or disclosure outside Cingular Wireless and its Affiliates except under written agreement.",
      "position": "footer"
    },
    {
      "type": "printed",
      "content": "07/26/17 Page 16 of 82 Public Records Request No.: 17-295 DOJ-OGR-00030734",
      "position": "footer"
    }
  ],
  "entities": {
    "people": [],
    "organizations": [
      "Cingular Wireless"
    ],
    "locations": [
      "NEW YORK NY",
      "WPALMBEACH FL",
      "CAMBRIDGE MA",
      "UK"
    ],
    "dates": [
      "12/14/2005",
      "12/19/05",
      "09/14/05",
      "07/26/17"
    ],
    "reference_numbers": [
      "153497",
      "0043811863",
      "17-295",
      "DOJ-OGR-00030734"
    ]
  },
  "additional_notes": "The document appears to be a billed usage report from Cingular Wireless. It contains a detailed breakdown of calls made on a specific account number. The document is marked as 'PROPRIETARY AND CONFIDENTIAL' and is not for use or disclosure outside Cingular Wireless and its affiliates except under written agreement."
}