{
  "document_metadata": {
    "page_number": "1644",
    "document_number": "Epstein #76318-054",
    "date": "2019/07/24",
    "document_type": "email",
    "has_handwriting": false,
    "has_stamps": false
  },
  "full_text": "Page 1644 Epstein #76318-054 From [b(6); (b)(7)(C) To [b(6); (b)(7)(C) Date 2019/07/24 13:05 Subject: Epstein #76318-054 Attachments: TEXT.htm This inmate is now on Psychological Observation. He is requesting he be provided his legal paperwork while on this status, which is permitted. Can someone please provide this to him? Very respectfully, [b(6); (b)(7)(C) Forensic Psychologist LT, U.S. Public Health Service U.S. Department of Justice Federal Bureau of Prisons Metropolitan Correctional Center 150 Park Row New York, New York 10007 Office: 646.83 [b(6); (b)(7)(C) Fax: 646.836.7712 E-mail [b(6); (b)(7)(C) @bop.gov \"This message is intended for official use and may contain SENSITIVE information. If this message contains SENSITIVE information, it should be properly delivered, labeled, stored, and disposed of according to policy.\" Page 8274 DOJ-OGR-00025694",
  "text_blocks": [
    {
      "type": "printed",
      "content": "Epstein #76318-054",
      "position": "top"
    },
    {
      "type": "printed",
      "content": "From [b(6); (b)(7)(C)",
      "position": "top"
    },
    {
      "type": "printed",
      "content": "To [b(6); (b)(7)(C)",
      "position": "top"
    },
    {
      "type": "printed",
      "content": "Date 2019/07/24 13:05",
      "position": "top"
    },
    {
      "type": "printed",
      "content": "Subject: Epstein #76318-054",
      "position": "top"
    },
    {
      "type": "printed",
      "content": "Attachments: TEXT.htm",
      "position": "top"
    },
    {
      "type": "printed",
      "content": "This inmate is now on Psychological Observation. He is requesting he be provided his legal paperwork while on this status, which is permitted. Can someone please provide this to him?",
      "position": "middle"
    },
    {
      "type": "printed",
      "content": "Very respectfully,",
      "position": "middle"
    },
    {
      "type": "printed",
      "content": "[b(6); (b)(7)(C)",
      "position": "middle"
    },
    {
      "type": "printed",
      "content": "Forensic Psychologist LT, U.S. Public Health Service U.S. Department of Justice Federal Bureau of Prisons Metropolitan Correctional Center 150 Park Row New York, New York 10007 Office: 646.83 [b(6); (b)(7)(C) Fax: 646.836.7712 E-mail [b(6); (b)(7)(C) @bop.gov",
      "position": "middle"
    },
    {
      "type": "printed",
      "content": "\"This message is intended for official use and may contain SENSITIVE information. If this message contains SENSITIVE information, it should be properly delivered, labeled, stored, and disposed of according to policy.\"",
      "position": "bottom"
    },
    {
      "type": "printed",
      "content": "Page 8274 DOJ-OGR-00025694",
      "position": "footer"
    }
  ],
  "entities": {
    "people": [
      "Epstein"
    ],
    "organizations": [
      "U.S. Public Health Service",
      "U.S. Department of Justice",
      "Federal Bureau of Prisons",
      "Metropolitan Correctional Center"
    ],
    "locations": [
      "New York"
    ],
    "dates": [
      "2019/07/24"
    ],
    "reference_numbers": [
      "#76318-054",
      "DOJ-OGR-00025694"
    ]
  },
  "additional_notes": "The document contains redactions marked as [b(6); (b)(7)(C)]. The document appears to be an email regarding an inmate's request for legal paperwork while on Psychological Observation status."
}