{
  "document_metadata": {
    "page_number": "1",
    "document_number": "8224738189",
    "date": "12/04/2019",
    "document_type": "TECS - Advance Traveler Information - Traveler List",
    "has_handwriting": false,
    "has_stamps": false
  },
  "full_text": "U.S. Customs and Border Protection U.S. Department of Homeland Security TECS - Advance Traveler Information - Traveler List 12/04/2019 11:15 BOT Generated By: (b)(6);(b)(7)(C) Page 1 of 1 SUMMARY for Manifest ID: 8224738189 Mode of Travel Tail # I/O Private Air N212JE I Arrival Date Arrival Time Arrival Location Departure Date Departure Location 04/09/2019 09:11 TIST 04/09/2019 KPBI Conf. Traveler's Name (L, F, M) DOB Hit Doc Type Doc # Country Gender Status ESTA Status EVUS Status Error List of Travelers EPSTEIN, JEFFREY, EDWARD 01/20/1953 (b)(7)(E) P 566672615 USA M PAX NOT REQUIRED (b)(6)&(b)(7)(C) (b)(6)&(b)(7)(C) P (b)(6)&(b)(7)(C) USA M CRW NOT REQUIRED (b)(6)&(b)(7)(C) (b)(6)&(b)(7)(C) P (b)(6)&(b)(7)(C) USA M CR1 NOT REQUIRED (b)(6)&(b)(7)(C) (b)(6)&(b)(7)(C) P (b)(6)&(b)(7)(C) USA F PAX NOT REQUIRED Showing 4 record(s) out of 4 record(s) received. For Official Use Only / Law Enforcement Sensitive DOJ-OGR-00027401",
  "text_blocks": [
    {
      "type": "printed",
      "content": "U.S. Customs and Border Protection U.S. Department of Homeland Security TECS - Advance Traveler Information - Traveler List",
      "position": "header"
    },
    {
      "type": "printed",
      "content": "SUMMARY for Manifest ID: 8224738189",
      "position": "header"
    },
    {
      "type": "printed",
      "content": "List of Travelers",
      "position": "header"
    },
    {
      "type": "printed",
      "content": "Showing 4 record(s) out of 4 record(s) received.",
      "position": "footer"
    },
    {
      "type": "printed",
      "content": "For Official Use Only / Law Enforcement Sensitive",
      "position": "footer"
    }
  ],
  "entities": {
    "people": [
      "JEFFREY EDWARD EPSTEIN"
    ],
    "organizations": [
      "U.S. Customs and Border Protection",
      "U.S. Department of Homeland Security"
    ],
    "locations": [
      "USA",
      "TIST",
      "KPBI"
    ],
    "dates": [
      "12/04/2019",
      "01/20/1953",
      "04/09/2019"
    ],
    "reference_numbers": [
      "8224738189",
      "566672615",
      "N212JE",
      "DOJ-OGR-00027401"
    ]
  },
  "additional_notes": "The document contains redacted information marked as (b)(6)&(b)(7)(C) and (b)(7)(E). The document is labeled 'For Official Use Only / Law Enforcement Sensitive'."
}