{
  "document_metadata": {
    "page_number": "3",
    "document_number": "5-2",
    "date": "09/09/2020",
    "document_type": "CRIMINAL DOCKET",
    "has_handwriting": false,
    "has_stamps": false
  },
  "full_text": "Case 20-3061, Document 5-2, 09/09/2020, 2927755, Page3 of 12\nAPPEAL,ECF\nU.S. District Court\nSouthern District of New York (Foley Square)\nCRIMINAL DOCKET FOR CASE #: 1:20-cr-00330-AJN All Defendants\nCase title: USA v. Maxwell                                  Date Filed: 06/29/2020\nAssigned to: Judge Alison J. Nathan\nDefendant (1)\nGhislaine Maxwell\nalso known as\nSealed Defendant 1\nrepresented by Christian R. Everdell\nCohne & Gresser LLP\n800 Third Avenue\nNew York, NY 10022\n212-707-7268\nFax: 212-957-4514\nEmail: ceverdell@cohengresser.com\nLEAD ATTORNEY\nATTORNEY TO BE NOTICED\nJeffrey S. Pagliuca\nHaddon Morgan and Foreman\n150 East 10th Avenue\nDenver, CO 80203\n(303)-831-7364\nFax: (303)-832-2628\nEmail: jpagliuca@hmflaw.com\nLEAD ATTORNEY\nATTORNEY TO BE NOTICED\nLaura A. Menninger\nHaddon, Morgan and Foreman, P.C.\n150 East Tenth Avenue\nDenver, CO 80203\n(303)-831-7364\nFax: (303)-832-2628\nEmail: lmenninger@hmflaw.com\nLEAD ATTORNEY\nATTORNEY TO BE NOTICED\nMark Stewart Cohen\nCohne & Gresser, LLP (NYC)\n800 Third Avenue\nNew York, NY 10022\n(212) 957-7600\nFax: (212)957-4514\nEmail: mcohen@cohengresser.com\nLEAD ATTORNEY\nATTORNEY TO BE NOTICED\nPending Counts\n18:371.F CONSPIRACY TO\nENTICE MINORS TO TRAVEL\nTO ENGAGE IN ILLEGAL SEX\nACTS\n(1)\n18:371.F CONSPIRACY TO\nENTICE MINORS TO TRAVEL\nTO ENGAGE IN ILLEGAL SEX\nDisposition\nDOJ-OGR-00019266",
  "text_blocks": [
    {
      "type": "printed",
      "content": "Case 20-3061, Document 5-2, 09/09/2020, 2927755, Page3 of 12",
      "position": "header"
    },
    {
      "type": "printed",
      "content": "U.S. District Court\nSouthern District of New York (Foley Square)\nCRIMINAL DOCKET FOR CASE #: 1:20-cr-00330-AJN All Defendants",
      "position": "header"
    },
    {
      "type": "printed",
      "content": "Case title: USA v. Maxwell                                  Date Filed: 06/29/2020\nAssigned to: Judge Alison J. Nathan",
      "position": "header"
    },
    {
      "type": "printed",
      "content": "Defendant (1)\nGhislaine Maxwell\nalso known as\nSealed Defendant 1",
      "position": "body"
    },
    {
      "type": "printed",
      "content": "represented by Christian R. Everdell\nCohne & Gresser LLP\n800 Third Avenue\nNew York, NY 10022\n212-707-7268\nFax: 212-957-4514\nEmail: ceverdell@cohengresser.com\nLEAD ATTORNEY\nATTORNEY TO BE NOTICED",
      "position": "body"
    },
    {
      "type": "printed",
      "content": "Jeffrey S. Pagliuca\nHaddon Morgan and Foreman\n150 East 10th Avenue\nDenver, CO 80203\n(303)-831-7364\nFax: (303)-832-2628\nEmail: jpagliuca@hmflaw.com\nLEAD ATTORNEY\nATTORNEY TO BE NOTICED",
      "position": "body"
    },
    {
      "type": "printed",
      "content": "Laura A. Menninger\nHaddon, Morgan and Foreman, P.C.\n150 East Tenth Avenue\nDenver, CO 80203\n(303)-831-7364\nFax: (303)-832-2628\nEmail: lmenninger@hmflaw.com\nLEAD ATTORNEY\nATTORNEY TO BE NOTICED",
      "position": "body"
    },
    {
      "type": "printed",
      "content": "Mark Stewart Cohen\nCohne & Gresser, LLP (NYC)\n800 Third Avenue\nNew York, NY 10022\n(212) 957-7600\nFax: (212)957-4514\nEmail: mcohen@cohengresser.com\nLEAD ATTORNEY\nATTORNEY TO BE NOTICED",
      "position": "body"
    },
    {
      "type": "printed",
      "content": "Pending Counts\n18:371.F CONSPIRACY TO\nENTICE MINORS TO TRAVEL\nTO ENGAGE IN ILLEGAL SEX\nACTS\n(1)\n18:371.F CONSPIRACY TO\nENTICE MINORS TO TRAVEL\nTO ENGAGE IN ILLEGAL SEX",
      "position": "body"
    },
    {
      "type": "printed",
      "content": "Disposition",
      "position": "body"
    },
    {
      "type": "printed",
      "content": "DOJ-OGR-00019266",
      "position": "footer"
    }
  ],
  "entities": {
    "people": [
      "Ghislaine Maxwell",
      "Christian R. Everdell",
      "Jeffrey S. Pagliuca",
      "Laura A. Menninger",
      "Mark Stewart Cohen",
      "Alison J. Nathan"
    ],
    "organizations": [
      "Cohne & Gresser LLP",
      "Haddon Morgan and Foreman",
      "Haddon, Morgan and Foreman, P.C.",
      "U.S. District Court",
      "Southern District of New York"
    ],
    "locations": [
      "New York",
      "Denver",
      "Foley Square"
    ],
    "dates": [
      "09/09/2020",
      "06/29/2020"
    ],
    "reference_numbers": [
      "1:20-cr-00330-AJN",
      "20-3061",
      "5-2",
      "2927755",
      "DOJ-OGR-00019266"
    ]
  },
  "additional_notes": "The document appears to be a court docket sheet with printed text. There are no visible handwritten notes or stamps."
}